drslib/__init__.py
drslib/banner.py
drslib/cli_ui.py
drslib/debug.py
drslib/decorators.py
drslib/dict_utils.py
drslib/execute.py
drslib/fsdb.py
drslib/hash.py
drslib/interval.py
drslib/list_utils.py
drslib/logging.py
drslib/mediainfo.py
drslib/multiprocessing.py
drslib/os_detect.py
drslib/path_tools.py
drslib/py.typed
drslib/spinner.py
drslib/str_utils.py
drslib/stream.py
drslib/timing.py
drslib/utils.py
drslib/web_crawl.py
drs.drslib-0.10.0.dist-info/LICENSE
drs.drslib-0.10.0.dist-info/METADATA
drs.drslib-0.10.0.dist-info/WHEEL
drs.drslib-0.10.0.dist-info/top_level.txt
drs.drslib-0.10.0.dist-info/RECORD
