Metadata-Version: 2.1
Name: drs.drslib
Version: 0.10.0
Summary: a set of libraries by DavidRodriguezSoaresCUI
Author-email: DavidRodriguezSoaresCUI <fireblaze904+drscui@gmail.com>
License: CC0 1.0 Universal
Project-URL: Homepage, https://github.com/DavidRodriguezSoaresCUI/DRSlib
Project-URL: Bug Tracker, https://github.com/DavidRodriguezSoaresCUI/DRSlib/issues
Classifier: Programming Language :: Python :: 3
Classifier: License :: CC0 1.0 Universal (CC0 1.0) Public Domain Dedication
Classifier: Intended Audience :: Developers
Classifier: License :: CC0 1.0 Universal (CC0 1.0) Public Domain Dedication
Classifier: Operating System :: OS Independent
Classifier: Programming Language :: Python :: 3 :: Only
Classifier: Programming Language :: Python :: 3.7
Classifier: Programming Language :: Python :: 3.8
Classifier: Programming Language :: Python :: 3.9
Classifier: Topic :: Software Development :: Libraries :: Python Modules
Requires-Python: >=3.10
License-File: LICENSE
Requires-Dist: beautifulsoup4
Requires-Dist: numpy
Requires-Dist: psutil
Requires-Dist: send2trash
Provides-Extra: analyse
Requires-Dist: mypy; extra == "analyse"
Requires-Dist: bandit; extra == "analyse"
Requires-Dist: pylint; extra == "analyse"
Requires-Dist: flake8; extra == "analyse"
Provides-Extra: doc
Requires-Dist: furo>=2023; extra == "doc"
Requires-Dist: Sphinx>=6.1.3; extra == "doc"
Provides-Extra: test
Requires-Dist: pytest>=8.0.0; extra == "test"
Requires-Dist: pytest-cov>=4.0.0; extra == "test"
